hqueue.py
hqueue-0.2.0.dist-info/DESCRIPTION.rst
hqueue-0.2.0.dist-info/METADATA
hqueue-0.2.0.dist-info/RECORD
hqueue-0.2.0.dist-info/WHEEL
hqueue-0.2.0.dist-info/metadata.json
hqueue-0.2.0.dist-info/top_level.txt
hqueue-0.2.0.dist-info/zip-safe
