Metadata-Version: 2.0
Name: hqueue
Version: 0.2.0
Summary: asyncio.Queue with history
Home-page: https://github.com/hsharrison/history-queue
Author: Henry S. Harrison
Author-email: henry.schafer.harrison@gmail.com
License: BSD
Keywords: asyncio,deque,queue,history
Platform: UNKNOWN
Classifier: Development Status :: 3 - Alpha
Classifier: Intended Audience :: Developers
Classifier: License :: OSI Approved :: BSD License
Classifier: Programming Language :: Python
Classifier: Programming Language :: Python :: 3.5
Classifier: Topic :: Utilities
Provides-Extra: test
Requires-Dist: hypothesis; extra == 'test'
Requires-Dist: pytest; extra == 'test'
Requires-Dist: pytest-cov; extra == 'test'
Requires-Dist: toolz; extra == 'test'
